tweet_preprocesser/preprocesser.py
tweet_preprocesser-0.0.3.dist-info/METADATA
tweet_preprocesser-0.0.3.dist-info/WHEEL
tweet_preprocesser-0.0.3.dist-info/top_level.txt
tweet_preprocesser-0.0.3.dist-info/RECORD
